litebot/bot.py
litebot-0.0.1.dist-info/METADATA
litebot-0.0.1.dist-info/WHEEL
litebot-0.0.1.dist-info/top_level.txt
litebot-0.0.1.dist-info/RECORD
