Metadata-Version: 2.1
Name: litebot
Version: 0.0.1
Summary: Boilerplate code for building bots
Home-page: https://github.com/life-efficient/bots
Author: Harry Berg
Author-email: harryaberg@gmail.com
License: MIT
Keywords: scraping,bots
Platform: UNKNOWN
